Workbook
Name ProjectNames: 'Project Lookup'!$B$2:$B$39
Name WeeklyCapacityHrs: 'Team Member Info'!$B$7

Sheet Read Me
A1: IGT Team Member Capacity Intake Template
A3: Purpose
A4: Use this workbook to collect consistent capacity information from each person so their past/current 2-week allocation and upcoming 2-week allocation can be plugged into IGT_Resource_Planning-v1.2.xlsx.
A6: What each team member should complete
A7: 1. Complete the Team Member Info sheet first. Blue cells are inputs.
A8: 2. On Project Allocations, enter one row per project or work stream you spent time on.
A9: 3. Fill in Past/Current 2 Weeks % and Upcoming 2 Weeks % as whole numbers (25 = 25%).
A10: 4. Choose Confidence and Skills Alignment for each row so uncertain estimates and role/project fit issues are visible.
A11: 5. Use the Recurring Work Detail tab to capture ongoing operational work so your total capacity is not understated.
A12: 4. If a project is not listed, choose Other / Missing Project and describe it in Notes.
A13: 7. Check the Capacity Summary sheet before sending it back. Anything above 100% should be reviewed with your manager.
A15: Color Legend
A16: Blue | B16: Team member inputs
A17: Gray | B17: Formulas / calculated values
A18: Yellow | B18: Review needed
A19: Green | B19: Project list
A21: This version intentionally asks only for past/current 2-week and upcoming 2-week allocation inputs.

Sheet Team Member Info
A1: Team Member Info
A3: Name | D3: Quick guidance
A4: Role | D4: • Weekly Capacity should reflect actual available work hours, not automatically 40 if reduced.
A5: Manager | D5: • Past/current allocation helps identify where time has actually been going.
A6: Location / Time Zone | D6: • Upcoming allocation supports the next 8-week capacity vs. demand view.
A7: Weekly Capacity (hrs) | B7: 40 | D7: • Include recurring operational work, meetings, support, and maintenance, not just named projects.
A8: Planning Start Date
A9: Submission Date | B9: =TODAY() -> 46223
A10: Any planned PTO / OOO during the 8-week window?
A11: Primary skill set / tools
A12: Comments / constraints

Sheet Project Lookup
A1: Project ID | B1: Project Name | C1: Default Category | D1: Status / Treatment | E1: Notes
A2: P0001 | B2: Atlas Migration | C2: Data Platform / Migration | D2: Select in Project Allocations as applicable
A3: P0002 | B3: Tableau Migration | C3: Data Platform / Migration | D3: Select in Project Allocations as applicable
A4: P0003 | B4: Expense & Budget Report | C4: Dashboard / Reporting | D4: Select in Project Allocations as applicable
A5: P0004 | B5: Game Performance Phases 2-3 | C5: Project | D5: Select in Project Allocations as applicable
A6: P0005 | B6: AID Dashboard | C6: Dashboard / Reporting | D6: Select in Project Allocations as applicable
A7: P0006 | B7: Combined EGM Day (Specialty) | C7: Project | D7: Select in Project Allocations as applicable
A8: P0007 | B8: R&O Custom Application | C8: Project | D8: Select in Project Allocations as applicable
A9: P0008 | B9: LBG-Executive Overview Dashboard | C9: Dashboard / Reporting | D9: Select in Project Allocations as applicable
A10: P0009 | B10: Commercial Reporting | C10: Dashboard / Reporting | D10: Select in Project Allocations as applicable
A11: P0010 | B11: Domenico weekly Reporting | C11: Dashboard / Reporting | D11: Select in Project Allocations as applicable
A12: P0011 | B12: Aggregated AIB | C12: Project | D12: Select in Project Allocations as applicable
A13: P0012 | B13: Math Model Comparison Dashboard | C13: Dashboard / Reporting | D13: Select in Project Allocations as applicable
... A39: N/A | B39: PTO / OOO / Holiday / Reduced Capacity | C39: Recurring / Non-project | D39: Select in Project Allocations as applicable

Sheet Project Allocations
A1: Project Allocations - 2-Week Team Member Entry
A2: Enter one row per project or work stream. Only fill in past/current 2-week and upcoming 2-week estimates as whole-number percentages (example: enter 25 for 25%). Dustin will derive the longer-range planning view separately.
A3: Project ID | B3: Project Name | C3: Past/Current 2 Weeks % | D3: Upcoming 2 Weeks % | E3: Confidence | F3: Skills Alignment | G3: Past/Current Hrs/Wk | H3: Upcoming Hrs/Wk | I3: Direction of Change | J3: Manager / Project Owner | K3: Key Deliverables / Work Description | L3: Notes
A4: =IFERROR(INDEX('Project Lookup'!$A:$A,MATCH(B4,'Project Lookup'!$B:$B,0)),"") | G4: =IF(C4="","",C4*WeeklyCapacityHrs/100) | H4: =IF(D4="","",D4*WeeklyCapacityHrs/100) | I4: =IF(OR(C4="",D4=""),"",IF(D4>C4,"Increasing",IF(D4<C4,"Decreasing","Flat")))
A5: =IFERROR(INDEX('Project Lookup'!$A:$A,MATCH(B5,'Project Lookup'!$B:$B,0)),"") | G5: =IF(C5="","",C5*WeeklyCapacityHrs/100) | H5: =IF(D5="","",D5*WeeklyCapacityHrs/100) | I5: =IF(OR(C5="",D5=""),"",IF(D5>C5,"Increasing",IF(D5<C5,"Decreasing","Flat")))
A6: =IFERROR(INDEX('Project Lookup'!$A:$A,MATCH(B6,'Project Lookup'!$B:$B,0)),"") | G6: =IF(C6="","",C6*WeeklyCapacityHrs/100) | H6: =IF(D6="","",D6*WeeklyCapacityHrs/100) | I6: =IF(OR(C6="",D6=""),"",IF(D6>C6,"Increasing",IF(D6<C6,"Decreasing","Flat")))
A7: =IFERROR(INDEX('Project Lookup'!$A:$A,MATCH(B7,'Project Lookup'!$B:$B,0)),"") | G7: =IF(C7="","",C7*WeeklyCapacityHrs/100) | H7: =IF(D7="","",D7*WeeklyCapacityHrs/100) | I7: =IF(OR(C7="",D7=""),"",IF(D7>C7,"Increasing",IF(D7<C7,"Decreasing","Flat")))
A8: =IFERROR(INDEX('Project Lookup'!$A:$A,MATCH(B8,'Project Lookup'!$B:$B,0)),"") | G8: =IF(C8="","",C8*WeeklyCapacityHrs/100) | H8: =IF(D8="","",D8*WeeklyCapacityHrs/100) | I8: =IF(OR(C8="",D8=""),"",IF(D8>C8,"Increasing",IF(D8<C8,"Decreasing","Flat")))
A9: =IFERROR(INDEX('Project Lookup'!$A:$A,MATCH(B9,'Project Lookup'!$B:$B,0)),"") | G9: =IF(C9="","",C9*WeeklyCapacityHrs/100) | H9: =IF(D9="","",D9*WeeklyCapacityHrs/100) | I9: =IF(OR(C9="",D9=""),"",IF(D9>C9,"Increasing",IF(D9<C9,"Decreasing","Flat")))
A10: =IFERROR(INDEX('Project Lookup'!$A:$A,MATCH(B10,'Project Lookup'!$B:$B,0)),"") | G10: =IF(C10="","",C10*WeeklyCapacityHrs/100) | H10: =IF(D10="","",D10*WeeklyCapacityHrs/100) | I10: =IF(OR(C10="",D10=""),"",IF(D10>C10,"Increasing",IF(D10<C10,"Decreasing","Flat")))
A11: =IFERROR(INDEX('Project Lookup'!$A:$A,MATCH(B11,'Project Lookup'!$B:$B,0)),"") | G11: =IF(C11="","",C11*WeeklyCapacityHrs/100) | H11: =IF(D11="","",D11*WeeklyCapacityHrs/100) | I11: =IF(OR(C11="",D11=""),"",IF(D11>C11,"Increasing",IF(D11<C11,"Decreasing","Flat")))
A12: =IFERROR(INDEX('Project Lookup'!$A:$A,MATCH(B12,'Project Lookup'!$B:$B,0)),"") | G12: =IF(C12="","",C12*WeeklyCapacityHrs/100) | H12: =IF(D12="","",D12*WeeklyCapacityHrs/100) | I12: =IF(OR(C12="",D12=""),"",IF(D12>C12,"Increasing",IF(D12<C12,"Decreasing","Flat")))
A13: =IFERROR(INDEX('Project Lookup'!$A:$A,MATCH(B13,'Project Lookup'!$B:$B,0)),"") | G13: =IF(C13="","",C13*WeeklyCapacityHrs/100) | H13: =IF(D13="","",D13*WeeklyCapacityHrs/100) | I13: =IF(OR(C13="",D13=""),"",IF(D13>C13,"Increasing",IF(D13<C13,"Decreasing","Flat")))
A14: =IFERROR(INDEX('Project Lookup'!$A:$A,MATCH(B14,'Project Lookup'!$B:$B,0)),"") | G14: =IF(C14="","",C14*WeeklyCapacityHrs/100) | H14: =IF(D14="","",D14*WeeklyCapacityHrs/100) | I14: =IF(OR(C14="",D14=""),"",IF(D14>C14,"Increasing",IF(D14<C14,"Decreasing","Flat")))
A15: =IFERROR(INDEX('Project Lookup'!$A:$A,MATCH(B15,'Project Lookup'!$B:$B,0)),"") | G15: =IF(C15="","",C15*WeeklyCapacityHrs/100) | H15: =IF(D15="","",D15*WeeklyCapacityHrs/100) | I15: =IF(OR(C15="",D15=""),"",IF(D15>C15,"Increasing",IF(D15<C15,"Decreasing","Flat")))
... A63: =IFERROR(INDEX('Project Lookup'!$A:$A,MATCH(B63,'Project Lookup'!$B:$B,0)),"") | G63: =IF(C63="","",C63*WeeklyCapacityHrs/100) | H63: =IF(D63="","",D63*WeeklyCapacityHrs/100) | I63: =IF(OR(C63="",D63=""),"",IF(D63>C63,"Increasing",IF(D63<C63,"Decreasing","Flat")))
A64: TOTAL | C64: =SUM(C4:C63) -> 0 | D64: =SUM(D4:D63) -> 0 | G64: =SUM(G4:G63) -> 0 | H64: =SUM(H4:H63) -> 0

Sheet Recurring Work Detail
A1: Recurring Responsibilities / Non-project Work Detail
A2: Use this sheet when recurring or operational work needs more detail than a single project allocation row.
A3: Category | B3: Description | C3: Frequency | D3: Avg Hrs / Week | E3: Backup / SME | F3: Notes

Sheet Capacity Summary
A1: Capacity Summary
A2: This summary uses only past/current 2-week and upcoming 2-week information. Percentages are entered as whole numbers on the Project Allocations tab.
A4: Metric | B4: Value | C4: Unit | D4: Review Flag
A5: Weekly Capacity | B5: =WeeklyCapacityHrs -> 40 | C5: hours
A6: Past/Current 2 Weeks Total Allocation | B6: =SUM('Project Allocations'!C4:C63) -> 0 | C6: % | D6: =IF(B6>100,"Over 100% - review",IF(B6>=80,"Watch","Healthy")) -> Healthy
A7: Past/Current Allocated Hrs/Wk | B7: =B6*B5/100 -> 0 | C7: hours/week
A8: Upcoming 2 Weeks Total Allocation | B8: =SUM('Project Allocations'!D4:D63) -> 0 | C8: % | D8: =IF(B8>100,"Over 100% - review",IF(B8>=80,"Watch","Healthy")) -> Healthy
A9: Upcoming Allocated Hrs/Wk | B9: =B8*B5/100 -> 0 | C9: hours/week
A10: Net Allocation Change | B10: =B8-B6 -> 0 | C10: percentage points
A11: Low Confidence Items | B11: =COUNTIF('Project Allocations'!E4:E63,"Low") -> 0 | C11: count | D11: =IF(B11>0,"Review","")
A12: Weak Skills Match Items | B12: =COUNTIF('Project Allocations'!F4:F63,"Weak Match") -> 0 | C12: count | D12: =IF(B12>0,"Review","")
A14: Top handoff guidance
A15: • If Upcoming 2 Weeks total is over 100%, review priority and possible reallocation.
A16: • Low confidence entries mean the next 2-week plan is uncertain and may need manager validation.
A17: • Weak skills-match entries may indicate the person is not on the best-fit work or is carrying avoidable support/maintenance load.
A18: • Use the Upcoming 2 Weeks allocation as the primary near-term demand input for the master resource planning workbook.
